pyproxypattern/__init__.py
pyproxypattern/proxy.py
pyproxypattern-0.0.1.dist-info/LICENSE
pyproxypattern-0.0.1.dist-info/METADATA
pyproxypattern-0.0.1.dist-info/WHEEL
pyproxypattern-0.0.1.dist-info/top_level.txt
pyproxypattern-0.0.1.dist-info/RECORD
