Metadata-Version: 2.1
Name: pyproxypattern
Version: 0.0.1
Summary: My package description
Home-page: https://github.com/Python-Tools/pyproxypattern
Author: hsz
Author-email: hsz1273327@gmail.com
License: MIT License
Keywords: proxy
Platform: UNKNOWN
Classifier: License :: OSI Approved :: MIT License
Classifier: Programming Language :: Python :: 3.6
Classifier: Programming Language :: Python :: 3.7
Classifier: Programming Language :: Python :: 3.8
Classifier: Programming Language :: Python :: 3.9
